itela_autoqa/__init__.py
itela_autoqa/ai.py
itela_autoqa/cli.py
itela_autoqa/config.py
itela_autoqa/utils.py
itela_autoqa-0.0.2.dist-info/METADATA
itela_autoqa-0.0.2.dist-info/WHEEL
itela_autoqa-0.0.2.dist-info/entry_points.txt
itela_autoqa-0.0.2.dist-info/top_level.txt
itela_autoqa-0.0.2.dist-info/RECORD
