Metadata-Version: 2.1
Name: itela-autoqa
Version: 0.0.2
Summary: iTelaSoft AI QA Automation CLI Tool
Home-page: https://git.itelasoft.com.au/chamara.herath/itelasoft-autoqa-tool
Author: Chamara Herath
Author-email: chamara.herath@itelasoft.com
Classifier: Programming Language :: Python :: 3
Classifier: License :: OSI Approved :: MIT License
Classifier: Operating System :: OS Independent
Requires-Python: >=3.8
Requires-Dist: openai<1.44,>=1.43.1
Requires-Dist: playwright<1.47,>=1.46.0
Requires-Dist: uuid==1.30
